nzrrest/__init__.py
nzrrest/app.py
nzrrest/cli.py
nzrrest/db.py
nzrrest/exceptions.py
nzrrest/middleware.py
nzrrest/requests.py
nzrrest/responses.py
nzrrest/routing.py
nzrrest/serializers.py
nzrrest/validators.py
nzrrest/ai/__init__.py
nzrrest/ai/context.py
nzrrest/ai/models.py
nzrrest/ai/protocol.py
nzrrest/ai/registry.py
nzrrest-0.1.0.dist-info/METADATA
nzrrest-0.1.0.dist-info/WHEEL
nzrrest-0.1.0.dist-info/entry_points.txt
nzrrest-0.1.0.dist-info/licenses/LICENSE
nzrrest-0.1.0.dist-info/RECORD
