Metadata-Version: 2.4
Name: nzrrest
Version: 0.1.0
Summary: Modern async Python framework for AI APIs with native Model Context Protocol (MCP) support
Project-URL: Homepage, https://github.com/nzrrest/nzrrest
Project-URL: Documentation, https://nzrrest.readthedocs.io
Project-URL: Repository, https://github.com/nzrrest/nzrrest
Project-URL: Bug Tracker, https://github.com/nzrrest/nzrrest/issues
Project-URL: Changelog, https://github.com/nzrrest/nzrrest/blob/main/CHANGELOG.md
Author-email: nzrRest Team <alairjt@gmail.com>
License: MIT
License-File: LICENSE
Keywords: ai,api,async,framework,machine-learning,mcp,n8n
Classifier: Development Status :: 4 - Beta
Classifier: Framework :: AsyncIO
Classifier: Intended Audience :: Developers
Classifier: License :: OSI Approved :: MIT License
Classifier: Operating System :: OS Independent
Classifier: Programming Language :: Python :: 3
Classifier: Programming Language :: Python :: 3.11
Classifier: Programming Language :: Python :: 3.12
Classifier: Programming Language :: Python :: 3.13
Classifier: Topic :: Internet :: WWW/HTTP :: HTTP Servers
Classifier: Topic :: Scientific/Engineering :: Artificial Intelligence
Classifier: Topic :: Software Development :: Libraries :: Application Frameworks
Classifier: Topic :: Software Development :: Libraries :: Python Modules
Requires-Python: >=3.11
Requires-Dist: aiofiles>=23.0.0
Requires-Dist: aiosqlite>=0.19.0
Requires-Dist: alembic>=1.12.0
Requires-Dist: asyncpg>=0.28.0
Requires-Dist: email-validator>=2.0.0
Requires-Dist: fastapi>=0.104.0
Requires-Dist: passlib[bcrypt]>=1.7.4
Requires-Dist: pydantic>=2.0.0
Requires-Dist: python-jose[cryptography]>=3.3.0
Requires-Dist: python-multipart>=0.0.6
Requires-Dist: rich>=13.0.0
Requires-Dist: sqlalchemy[asyncio]>=2.0.0
Requires-Dist: starlette>=0.27.0
Requires-Dist: typer[all]>=0.9.0
Requires-Dist: uvicorn[standard]>=0.24.0
Provides-Extra: ai
Requires-Dist: anthropic>=0.7.0; extra == 'ai'
Requires-Dist: openai>=1.0.0; extra == 'ai'
Requires-Dist: torch>=2.0.0; extra == 'ai'
Requires-Dist: transformers>=4.30.0; extra == 'ai'
Provides-Extra: dev
Requires-Dist: black>=23.0.0; extra == 'dev'
Requires-Dist: flake8>=6.1.0; extra == 'dev'
Requires-Dist: httpx>=0.25.0; extra == 'dev'
Requires-Dist: isort>=5.12.0; extra == 'dev'
Requires-Dist: mypy>=1.6.0; extra == 'dev'
Requires-Dist: pre-commit>=3.5.0; extra == 'dev'
Requires-Dist: pytest-asyncio>=0.21.0; extra == 'dev'
Requires-Dist: pytest-cov>=4.1.0; extra == 'dev'
Requires-Dist: pytest>=7.4.0; extra == 'dev'
Provides-Extra: docs
Requires-Dist: mkdocs-material>=9.4.0; extra == 'docs'
Requires-Dist: mkdocs-mermaid2-plugin>=1.1.0; extra == 'docs'
Requires-Dist: mkdocs>=1.5.0; extra == 'docs'
Provides-Extra: monitoring
Requires-Dist: prometheus-client>=0.17.0; extra == 'monitoring'
Requires-Dist: sentry-sdk>=1.35.0; extra == 'monitoring'
Requires-Dist: structlog>=23.0.0; extra == 'monitoring'
Provides-Extra: redis
Requires-Dist: aioredis>=2.0.0; extra == 'redis'
Requires-Dist: redis>=5.0.0; extra == 'redis'
